{
    "module": "pygsti.models.explicitmodel",
    "class": "ExplicitOpModel",
    "version": 0,
    "state_space": {
        "module": "pygsti.baseobjs.statespace",
        "class": "ExplicitStateSpace",
        "version": 0,
        "labels": [
            [
                0
            ]
        ],
        "unitary_space_dimensions": [
            [
                2
            ]
        ],
        "types": [
            [
                "Q"
            ]
        ]
    },
    "basis": {
        "module": "pygsti.baseobjs.basis",
        "class": "BuiltinBasis",
        "version": 0,
        "name": "pp",
        "sparse": false,
        "state_space": {
            "module": "pygsti.baseobjs.statespace",
            "class": "ExplicitStateSpace",
            "version": 0,
            "labels": [
                [
                    0
                ]
            ],
            "unitary_space_dimensions": [
                [
                    2
                ]
            ],
            "types": [
                [
                    "Q"
                ]
            ]
        }
    },
    "default_gate_type": "CPTP",
    "default_prep_type": [
        "CPTP"
    ],
    "default_povm_type": [
        "CPTP"
    ],
    "default_instrument_type": [
        "full TP"
    ],
    "prep_prefix": "rho",
    "effect_prefix": "E",
    "gate_prefix": "G",
    "povm_prefix": "M",
    "instrument_prefix": "I",
    "evotype": "densitymx",
    "simulator": {
        "module": "pygsti.forwardsims.matrixforwardsim",
        "class": "MatrixForwardSimulator",
        "version": 0,
        "mode": "time_independent"
    },
    "default_gauge_group": {
        "module": "pygsti.models.gaugegroup",
        "class": "UnitaryGaugeGroup",
        "version": 0,
        "state_space_dimension": 4,
        "evotype": "densitymx",
        "basis": {
            "module": "pygsti.baseobjs.basis",
            "class": "BuiltinBasis",
            "version": 0,
            "name": "pp",
            "sparse": false,
            "state_space": {
                "module": "pygsti.baseobjs.statespace",
                "class": "ExplicitStateSpace",
                "version": 0,
                "labels": [
                    [
                        0
                    ]
                ],
                "unitary_space_dimensions": [
                    [
                        2
                    ]
                ],
                "types": [
                    [
                        "Q"
                    ]
                ]
            }
        }
    },
    "modelmembers": {
        "0": {
            "module": "pygsti.modelmembers.operations.lindbladerrorgen",
            "class": "LindbladErrorgen",
            "submembers": [],
            "state_space": {
                "module": "pygsti.baseobjs.statespace",
                "class": "QubitSpace",
                "version": 0,
                "qudit_labels": [
                    0
                ],
                "qudit_udims": [
                    2
                ],
                "qubit_labels": [
                    0
                ]
            },
            "evotype": "densitymx",
            "model_parameter_indices": [
                0,
                1,
                2,
                3,
                4,
                5,
                6,
                7,
                8,
                9,
                10,
                11
            ],
            "relative_submember_parameter_indices": [],
            "parameter_labels": [
                "X Hamiltonian error coefficient",
                "Y Hamiltonian error coefficient",
                "Z Hamiltonian error coefficient",
                "X diagonal element of non-H coeff Cholesky decomp",
                "Im[(X,Y) element of non-H coeff Cholesky decomp]",
                "Im[(X,Z) element of non-H coeff Cholesky decomp]",
                "Re[(Y,X) element of non-H coeff Cholesky decomp]",
                "Y diagonal element of non-H coeff Cholesky decomp",
                "Im[(Y,Z) element of non-H coeff Cholesky decomp]",
                "Re[(Z,X) element of non-H coeff Cholesky decomp]",
                "Re[(Z,Y) element of non-H coeff Cholesky decomp]",
                "Z diagonal element of non-H coeff Cholesky decomp"
            ],
            "parameter_bounds": null,
            "rep_type": "sparse superop",
            "matrix_basis": {
                "module": "pygsti.baseobjs.basis",
                "class": "BuiltinBasis",
                "version": 0,
                "name": "pp",
                "sparse": true,
                "state_space": {
                    "module": "pygsti.baseobjs.statespace",
                    "class": "ExplicitStateSpace",
                    "version": 0,
                    "labels": [
                        [
                            0
                        ]
                    ],
                    "unitary_space_dimensions": [
                        [
                            2
                        ]
                    ],
                    "types": [
                        [
                            "Q"
                        ]
                    ]
                }
            },
            "coefficient_blocks": [
                {
                    "module": "pygsti.modelmembers.operations.lindbladcoefficients",
                    "class": "LindbladCoefficientBlock",
                    "version": 0,
                    "block_type": "ham",
                    "parameterization_mode": "elements",
                    "basis_element_labels": [
                        "X",
                        "Y",
                        "Z"
                    ],
                    "basis": {
                        "module": "pygsti.baseobjs.basis",
                        "class": "BuiltinBasis",
                        "version": 0,
                        "name": "PP",
                        "sparse": true,
                        "state_space": {
                            "module": "pygsti.baseobjs.statespace",
                            "class": "QubitSpace",
                            "version": 0,
                            "qudit_labels": [
                                0
                            ],
                            "qudit_udims": [
                                2
                            ],
                            "qubit_labels": [
                                0
                            ]
                        }
                    },
                    "block_data": [
                        -0.1777600145182329,
                        0.09616106755054507,
                        0.06741932958001697
                    ]
                },
                {
                    "module": "pygsti.modelmembers.operations.lindbladcoefficients",
                    "class": "LindbladCoefficientBlock",
                    "version": 0,
                    "block_type": "other",
                    "parameterization_mode": "cholesky",
                    "basis_element_labels": [
                        "X",
                        "Y",
                        "Z"
                    ],
                    "basis": {
                        "module": "pygsti.baseobjs.basis",
                        "class": "BuiltinBasis",
                        "version": 0,
                        "name": "PP",
                        "sparse": true,
                        "state_space": {
                            "module": "pygsti.baseobjs.statespace",
                            "class": "QubitSpace",
                            "version": 0,
                            "qudit_labels": [
                                0
                            ],
                            "qudit_udims": [
                                2
                            ],
                            "qubit_labels": [
                                0
                            ]
                        }
                    },
                    "block_data": [
                        [
                            "(0.00041437181128061676+0j)",
                            "(-3.9790393247731454e-05+0.0005722616772122196j)",
                            "(-0.0005541157654485094+0.0005317753141076654j)"
                        ],
                        [
                            "(-3.9790393247731454e-05-0.0005722616772122196j)",
                            "(0.0007941421619856153+0j)",
                            "(0.0007877308242299915+0.0007140462942901645j)"
                        ],
                        [
                            "(-0.0005541157654485094-0.0005317753141076654j)",
                            "(0.0007877308242299915-0.0007140462942901645j)",
                            "(0.001427670575094676+0j)"
                        ]
                    ]
                }
            ]
        },
        "1": {
            "module": "pygsti.modelmembers.operations.experrorgenop",
            "class": "ExpErrorgenOp",
            "submembers": [
                0
            ],
            "state_space": {
                "module": "pygsti.baseobjs.statespace",
                "class": "QubitSpace",
                "version": 0,
                "qudit_labels": [
                    0
                ],
                "qudit_udims": [
                    2
                ],
                "qubit_labels": [
                    0
                ]
            },
            "evotype": "densitymx",
            "model_parameter_indices": [
                0,
                1,
                2,
                3,
                4,
                5,
                6,
                7,
                8,
                9,
                10,
                11
            ],
            "relative_submember_parameter_indices": [
                [
                    0,
                    1,
                    2,
                    3,
                    4,
                    5,
                    6,
                    7,
                    8,
                    9,
                    10,
                    11
                ]
            ],
            "parameter_labels": null,
            "parameter_bounds": null
        },
        "2": {
            "module": "pygsti.modelmembers.states.staticpurestate",
            "class": "StaticPureState",
            "submembers": [],
            "state_space": {
                "module": "pygsti.baseobjs.statespace",
                "class": "ExplicitStateSpace",
                "version": 0,
                "labels": [
                    [
                        0
                    ]
                ],
                "unitary_space_dimensions": [
                    [
                        2
                    ]
                ],
                "types": [
                    [
                        "Q"
                    ]
                ]
            },
            "evotype": "densitymx",
            "model_parameter_indices": [],
            "relative_submember_parameter_indices": [],
            "parameter_labels": null,
            "parameter_bounds": null,
            "dense_state_vector": [
                "(1+0j)",
                "0j"
            ],
            "basis": {
                "module": "pygsti.baseobjs.basis",
                "class": "BuiltinBasis",
                "version": 0,
                "name": "pp",
                "sparse": false,
                "state_space": {
                    "module": "pygsti.baseobjs.statespace",
                    "class": "ExplicitStateSpace",
                    "version": 0,
                    "labels": [
                        [
                            0
                        ]
                    ],
                    "unitary_space_dimensions": [
                        [
                            2
                        ]
                    ],
                    "types": [
                        [
                            "Q"
                        ]
                    ]
                }
            }
        },
        "3": {
            "module": "pygsti.modelmembers.states.composedstate",
            "class": "ComposedState",
            "submembers": [
                1,
                2
            ],
            "state_space": {
                "module": "pygsti.baseobjs.statespace",
                "class": "ExplicitStateSpace",
                "version": 0,
                "labels": [
                    [
                        0
                    ]
                ],
                "unitary_space_dimensions": [
                    [
                        2
                    ]
                ],
                "types": [
                    [
                        "Q"
                    ]
                ]
            },
            "evotype": "densitymx",
            "model_parameter_indices": [
                0,
                1,
                2,
                3,
                4,
                5,
                6,
                7,
                8,
                9,
                10,
                11
            ],
            "relative_submember_parameter_indices": [
                [
                    0,
                    1,
                    2,
                    3,
                    4,
                    5,
                    6,
                    7,
                    8,
                    9,
                    10,
                    11
                ],
                []
            ],
            "parameter_labels": null,
            "parameter_bounds": null,
            "memberdict_types": [
                "preps"
            ],
            "memberdict_labels": [
                "rho0"
            ]
        },
        "4": {
            "module": "pygsti.modelmembers.operations.lindbladerrorgen",
            "class": "LindbladErrorgen",
            "submembers": [],
            "state_space": {
                "module": "pygsti.baseobjs.statespace",
                "class": "ExplicitStateSpace",
                "version": 0,
                "labels": [
                    [
                        0
                    ]
                ],
                "unitary_space_dimensions": [
                    [
                        2
                    ]
                ],
                "types": [
                    [
                        "Q"
                    ]
                ]
            },
            "evotype": "densitymx",
            "model_parameter_indices": [
                12,
                13,
                14,
                15,
                16,
                17,
                18,
                19,
                20,
                21,
                22,
                23
            ],
            "relative_submember_parameter_indices": [],
            "parameter_labels": [
                "X Hamiltonian error coefficient",
                "Y Hamiltonian error coefficient",
                "Z Hamiltonian error coefficient",
                "X diagonal element of non-H coeff Cholesky decomp",
                "Im[(X,Y) element of non-H coeff Cholesky decomp]",
                "Im[(X,Z) element of non-H coeff Cholesky decomp]",
                "Re[(Y,X) element of non-H coeff Cholesky decomp]",
                "Y diagonal element of non-H coeff Cholesky decomp",
                "Im[(Y,Z) element of non-H coeff Cholesky decomp]",
                "Re[(Z,X) element of non-H coeff Cholesky decomp]",
                "Re[(Z,Y) element of non-H coeff Cholesky decomp]",
                "Z diagonal element of non-H coeff Cholesky decomp"
            ],
            "parameter_bounds": null,
            "rep_type": "sparse superop",
            "matrix_basis": {
                "module": "pygsti.baseobjs.basis",
                "class": "BuiltinBasis",
                "version": 0,
                "name": "pp",
                "sparse": true,
                "state_space": {
                    "module": "pygsti.baseobjs.statespace",
                    "class": "ExplicitStateSpace",
                    "version": 0,
                    "labels": [
                        [
                            0
                        ]
                    ],
                    "unitary_space_dimensions": [
                        [
                            2
                        ]
                    ],
                    "types": [
                        [
                            "Q"
                        ]
                    ]
                }
            },
            "coefficient_blocks": [
                {
                    "module": "pygsti.modelmembers.operations.lindbladcoefficients",
                    "class": "LindbladCoefficientBlock",
                    "version": 0,
                    "block_type": "ham",
                    "parameterization_mode": "elements",
                    "basis_element_labels": [
                        "X",
                        "Y",
                        "Z"
                    ],
                    "basis": {
                        "module": "pygsti.baseobjs.basis",
                        "class": "BuiltinBasis",
                        "version": 0,
                        "name": "PP",
                        "sparse": true,
                        "state_space": {
                            "module": "pygsti.baseobjs.statespace",
                            "class": "QubitSpace",
                            "version": 0,
                            "qudit_labels": [
                                0
                            ],
                            "qudit_udims": [
                                2
                            ],
                            "qubit_labels": [
                                0
                            ]
                        }
                    },
                    "block_data": [
                        0.09384528778812706,
                        -0.2466860647188677,
                        -0.06530569369446938
                    ]
                },
                {
                    "module": "pygsti.modelmembers.operations.lindbladcoefficients",
                    "class": "LindbladCoefficientBlock",
                    "version": 0,
                    "block_type": "other",
                    "parameterization_mode": "cholesky",
                    "basis_element_labels": [
                        "X",
                        "Y",
                        "Z"
                    ],
                    "basis": {
                        "module": "pygsti.baseobjs.basis",
                        "class": "BuiltinBasis",
                        "version": 0,
                        "name": "PP",
                        "sparse": true,
                        "state_space": {
                            "module": "pygsti.baseobjs.statespace",
                            "class": "QubitSpace",
                            "version": 0,
                            "qudit_labels": [
                                0
                            ],
                            "qudit_udims": [
                                2
                            ],
                            "qubit_labels": [
                                0
                            ]
                        }
                    },
                    "block_data": [
                        [
                            "(0.08339828569089812+0j)",
                            "(0.006397654636221042-0.08645548537600113j)",
                            "(-0.012506714676553567-0.019837796223151658j)"
                        ],
                        [
                            "(0.006397654636221042+0.08645548537600113j)",
                            "(0.09011553265399323+0j)",
                            "(0.01960559076450796-0.014486981973867438j)"
                        ],
                        [
                            "(-0.012506714676553567+0.019837796223151658j)",
                            "(0.01960559076450796+0.014486981973867438j)",
                            "(0.006594333298719663+0j)"
                        ]
                    ]
                }
            ]
        },
        "5": {
            "module": "pygsti.modelmembers.operations.experrorgenop",
            "class": "ExpErrorgenOp",
            "submembers": [
                4
            ],
            "state_space": {
                "module": "pygsti.baseobjs.statespace",
                "class": "ExplicitStateSpace",
                "version": 0,
                "labels": [
                    [
                        0
                    ]
                ],
                "unitary_space_dimensions": [
                    [
                        2
                    ]
                ],
                "types": [
                    [
                        "Q"
                    ]
                ]
            },
            "evotype": "densitymx",
            "model_parameter_indices": [
                12,
                13,
                14,
                15,
                16,
                17,
                18,
                19,
                20,
                21,
                22,
                23
            ],
            "relative_submember_parameter_indices": [
                [
                    0,
                    1,
                    2,
                    3,
                    4,
                    5,
                    6,
                    7,
                    8,
                    9,
                    10,
                    11
                ]
            ],
            "parameter_labels": null,
            "parameter_bounds": null
        },
        "6": {
            "module": "pygsti.modelmembers.povms.computationalpovm",
            "class": "ComputationalBasisPOVM",
            "submembers": [],
            "state_space": {
                "module": "pygsti.baseobjs.statespace",
                "class": "QubitSpace",
                "version": 0,
                "qudit_labels": [
                    0
                ],
                "qudit_udims": [
                    2
                ],
                "qubit_labels": [
                    0
                ]
            },
            "evotype": "default",
            "model_parameter_indices": [],
            "relative_submember_parameter_indices": [],
            "parameter_labels": null,
            "parameter_bounds": null,
            "nqubits": 1,
            "qubit_filter": null
        },
        "7": {
            "module": "pygsti.modelmembers.povms.composedpovm",
            "class": "ComposedPOVM",
            "submembers": [
                5,
                6
            ],
            "state_space": {
                "module": "pygsti.baseobjs.statespace",
                "class": "ExplicitStateSpace",
                "version": 0,
                "labels": [
                    [
                        0
                    ]
                ],
                "unitary_space_dimensions": [
                    [
                        2
                    ]
                ],
                "types": [
                    [
                        "Q"
                    ]
                ]
            },
            "evotype": "densitymx",
            "model_parameter_indices": [
                12,
                13,
                14,
                15,
                16,
                17,
                18,
                19,
                20,
                21,
                22,
                23
            ],
            "relative_submember_parameter_indices": [
                [
                    0,
                    1,
                    2,
                    3,
                    4,
                    5,
                    6,
                    7,
                    8,
                    9,
                    10,
                    11
                ],
                []
            ],
            "parameter_labels": null,
            "parameter_bounds": null,
            "matrix_basis": {
                "module": "pygsti.baseobjs.basis",
                "class": "BuiltinBasis",
                "version": 0,
                "name": "pp",
                "sparse": false,
                "state_space": {
                    "module": "pygsti.baseobjs.statespace",
                    "class": "ExplicitStateSpace",
                    "version": 0,
                    "labels": [
                        [
                            0
                        ]
                    ],
                    "unitary_space_dimensions": [
                        [
                            2
                        ]
                    ],
                    "types": [
                        [
                            "Q"
                        ]
                    ]
                }
            },
            "memberdict_types": [
                "povms"
            ],
            "memberdict_labels": [
                "Mdefault"
            ]
        },
        "8": {
            "module": "pygsti.modelmembers.operations.staticunitaryop",
            "class": "StaticUnitaryOp",
            "submembers": [],
            "state_space": {
                "module": "pygsti.baseobjs.statespace",
                "class": "ExplicitStateSpace",
                "version": 0,
                "labels": [
                    [
                        0
                    ]
                ],
                "unitary_space_dimensions": [
                    [
                        2
                    ]
                ],
                "types": [
                    [
                        "Q"
                    ]
                ]
            },
            "evotype": "densitymx",
            "model_parameter_indices": [],
            "relative_submember_parameter_indices": [],
            "parameter_labels": null,
            "parameter_bounds": null,
            "dense_matrix": [
                [
                    "(1+0j)",
                    "0j"
                ],
                [
                    "0j",
                    "(1+0j)"
                ]
            ],
            "basis": {
                "module": "pygsti.baseobjs.basis",
                "class": "BuiltinBasis",
                "version": 0,
                "name": "pp",
                "sparse": false,
                "state_space": {
                    "module": "pygsti.baseobjs.statespace",
                    "class": "ExplicitStateSpace",
                    "version": 0,
                    "labels": [
                        [
                            0
                        ]
                    ],
                    "unitary_space_dimensions": [
                        [
                            2
                        ]
                    ],
                    "types": [
                        [
                            "Q"
                        ]
                    ]
                }
            }
        },
        "9": {
            "module": "pygsti.modelmembers.operations.lindbladerrorgen",
            "class": "LindbladErrorgen",
            "submembers": [],
            "state_space": {
                "module": "pygsti.baseobjs.statespace",
                "class": "ExplicitStateSpace",
                "version": 0,
                "labels": [
                    [
                        0
                    ]
                ],
                "unitary_space_dimensions": [
                    [
                        2
                    ]
                ],
                "types": [
                    [
                        "Q"
                    ]
                ]
            },
            "evotype": "densitymx",
            "model_parameter_indices": [
                24,
                25,
                26,
                27,
                28,
                29,
                30,
                31,
                32,
                33,
                34,
                35
            ],
            "relative_submember_parameter_indices": [],
            "parameter_labels": [
                "X Hamiltonian error coefficient",
                "Y Hamiltonian error coefficient",
                "Z Hamiltonian error coefficient",
                "X diagonal element of non-H coeff Cholesky decomp",
                "Im[(X,Y) element of non-H coeff Cholesky decomp]",
                "Im[(X,Z) element of non-H coeff Cholesky decomp]",
                "Re[(Y,X) element of non-H coeff Cholesky decomp]",
                "Y diagonal element of non-H coeff Cholesky decomp",
                "Im[(Y,Z) element of non-H coeff Cholesky decomp]",
                "Re[(Z,X) element of non-H coeff Cholesky decomp]",
                "Re[(Z,Y) element of non-H coeff Cholesky decomp]",
                "Z diagonal element of non-H coeff Cholesky decomp"
            ],
            "parameter_bounds": null,
            "rep_type": "sparse superop",
            "matrix_basis": {
                "module": "pygsti.baseobjs.basis",
                "class": "BuiltinBasis",
                "version": 0,
                "name": "pp",
                "sparse": true,
                "state_space": {
                    "module": "pygsti.baseobjs.statespace",
                    "class": "ExplicitStateSpace",
                    "version": 0,
                    "labels": [
                        [
                            0
                        ]
                    ],
                    "unitary_space_dimensions": [
                        [
                            2
                        ]
                    ],
                    "types": [
                        [
                            "Q"
                        ]
                    ]
                }
            },
            "coefficient_blocks": [
                {
                    "module": "pygsti.modelmembers.operations.lindbladcoefficients",
                    "class": "LindbladCoefficientBlock",
                    "version": 0,
                    "block_type": "ham",
                    "parameterization_mode": "elements",
                    "basis_element_labels": [
                        "X",
                        "Y",
                        "Z"
                    ],
                    "basis": {
                        "module": "pygsti.baseobjs.basis",
                        "class": "BuiltinBasis",
                        "version": 0,
                        "name": "PP",
                        "sparse": true,
                        "state_space": {
                            "module": "pygsti.baseobjs.statespace",
                            "class": "QubitSpace",
                            "version": 0,
                            "qudit_labels": [
                                0
                            ],
                            "qudit_udims": [
                                2
                            ],
                            "qubit_labels": [
                                0
                            ]
                        }
                    },
                    "block_data": [
                        -0.20380461249468648,
                        0.059193503273701376,
                        -0.35979508650792613
                    ]
                },
                {
                    "module": "pygsti.modelmembers.operations.lindbladcoefficients",
                    "class": "LindbladCoefficientBlock",
                    "version": 0,
                    "block_type": "other",
                    "parameterization_mode": "cholesky",
                    "basis_element_labels": [
                        "X",
                        "Y",
                        "Z"
                    ],
                    "basis": {
                        "module": "pygsti.baseobjs.basis",
                        "class": "BuiltinBasis",
                        "version": 0,
                        "name": "PP",
                        "sparse": true,
                        "state_space": {
                            "module": "pygsti.baseobjs.statespace",
                            "class": "QubitSpace",
                            "version": 0,
                            "qudit_labels": [
                                0
                            ],
                            "qudit_udims": [
                                2
                            ],
                            "qubit_labels": [
                                0
                            ]
                        }
                    },
                    "block_data": [
                        [
                            "(0.054179136485615516+0j)",
                            "(-0.23119437140047824-0.09076062928563874j)",
                            "(0.30540121688225635+0.07283930101872677j)"
                        ],
                        [
                            "(-0.23119437140047824+0.09076062928563874j)",
                            "(1.3270011530173254+0j)",
                            "(-1.6251585725973219+0.2799549922398196j)"
                        ],
                        [
                            "(0.30540121688225635-0.07283930101872677j)",
                            "(-1.6251585725973219-0.2799549922398196j)",
                            "(2.064855125921808+0j)"
                        ]
                    ]
                }
            ]
        },
        "10": {
            "module": "pygsti.modelmembers.operations.experrorgenop",
            "class": "ExpErrorgenOp",
            "submembers": [
                9
            ],
            "state_space": {
                "module": "pygsti.baseobjs.statespace",
                "class": "ExplicitStateSpace",
                "version": 0,
                "labels": [
                    [
                        0
                    ]
                ],
                "unitary_space_dimensions": [
                    [
                        2
                    ]
                ],
                "types": [
                    [
                        "Q"
                    ]
                ]
            },
            "evotype": "densitymx",
            "model_parameter_indices": [
                24,
                25,
                26,
                27,
                28,
                29,
                30,
                31,
                32,
                33,
                34,
                35
            ],
            "relative_submember_parameter_indices": [
                [
                    0,
                    1,
                    2,
                    3,
                    4,
                    5,
                    6,
                    7,
                    8,
                    9,
                    10,
                    11
                ]
            ],
            "parameter_labels": null,
            "parameter_bounds": null
        },
        "11": {
            "module": "pygsti.modelmembers.operations.composedop",
            "class": "ComposedOp",
            "submembers": [
                8,
                10
            ],
            "state_space": {
                "module": "pygsti.baseobjs.statespace",
                "class": "ExplicitStateSpace",
                "version": 0,
                "labels": [
                    [
                        0
                    ]
                ],
                "unitary_space_dimensions": [
                    [
                        2
                    ]
                ],
                "types": [
                    [
                        "Q"
                    ]
                ]
            },
            "evotype": "densitymx",
            "model_parameter_indices": [
                24,
                25,
                26,
                27,
                28,
                29,
                30,
                31,
                32,
                33,
                34,
                35
            ],
            "relative_submember_parameter_indices": [
                [],
                [
                    0,
                    1,
                    2,
                    3,
                    4,
                    5,
                    6,
                    7,
                    8,
                    9,
                    10,
                    11
                ]
            ],
            "parameter_labels": null,
            "parameter_bounds": null,
            "memberdict_types": [
                "operations"
            ],
            "memberdict_labels": [
                "Gi:0"
            ]
        },
        "12": {
            "module": "pygsti.modelmembers.operations.staticunitaryop",
            "class": "StaticUnitaryOp",
            "submembers": [],
            "state_space": {
                "module": "pygsti.baseobjs.statespace",
                "class": "ExplicitStateSpace",
                "version": 0,
                "labels": [
                    [
                        0
                    ]
                ],
                "unitary_space_dimensions": [
                    [
                        2
                    ]
                ],
                "types": [
                    [
                        "Q"
                    ]
                ]
            },
            "evotype": "densitymx",
            "model_parameter_indices": [],
            "relative_submember_parameter_indices": [],
            "parameter_labels": null,
            "parameter_bounds": null,
            "dense_matrix": [
                [
                    "0.7071067811865475j",
                    "(0.7071067811865475+0j)"
                ],
                [
                    "(0.7071067811865477+0j)",
                    "0.7071067811865477j"
                ]
            ],
            "basis": {
                "module": "pygsti.baseobjs.basis",
                "class": "BuiltinBasis",
                "version": 0,
                "name": "pp",
                "sparse": false,
                "state_space": {
                    "module": "pygsti.baseobjs.statespace",
                    "class": "ExplicitStateSpace",
                    "version": 0,
                    "labels": [
                        [
                            0
                        ]
                    ],
                    "unitary_space_dimensions": [
                        [
                            2
                        ]
                    ],
                    "types": [
                        [
                            "Q"
                        ]
                    ]
                }
            }
        },
        "13": {
            "module": "pygsti.modelmembers.operations.lindbladerrorgen",
            "class": "LindbladErrorgen",
            "submembers": [],
            "state_space": {
                "module": "pygsti.baseobjs.statespace",
                "class": "ExplicitStateSpace",
                "version": 0,
                "labels": [
                    [
                        0
                    ]
                ],
                "unitary_space_dimensions": [
                    [
                        2
                    ]
                ],
                "types": [
                    [
                        "Q"
                    ]
                ]
            },
            "evotype": "densitymx",
            "model_parameter_indices": [
                36,
                37,
                38,
                39,
                40,
                41,
                42,
                43,
                44,
                45,
                46,
                47
            ],
            "relative_submember_parameter_indices": [],
            "parameter_labels": [
                "X Hamiltonian error coefficient",
                "Y Hamiltonian error coefficient",
                "Z Hamiltonian error coefficient",
                "X diagonal element of non-H coeff Cholesky decomp",
                "Im[(X,Y) element of non-H coeff Cholesky decomp]",
                "Im[(X,Z) element of non-H coeff Cholesky decomp]",
                "Re[(Y,X) element of non-H coeff Cholesky decomp]",
                "Y diagonal element of non-H coeff Cholesky decomp",
                "Im[(Y,Z) element of non-H coeff Cholesky decomp]",
                "Re[(Z,X) element of non-H coeff Cholesky decomp]",
                "Re[(Z,Y) element of non-H coeff Cholesky decomp]",
                "Z diagonal element of non-H coeff Cholesky decomp"
            ],
            "parameter_bounds": null,
            "rep_type": "sparse superop",
            "matrix_basis": {
                "module": "pygsti.baseobjs.basis",
                "class": "BuiltinBasis",
                "version": 0,
                "name": "pp",
                "sparse": true,
                "state_space": {
                    "module": "pygsti.baseobjs.statespace",
                    "class": "ExplicitStateSpace",
                    "version": 0,
                    "labels": [
                        [
                            0
                        ]
                    ],
                    "unitary_space_dimensions": [
                        [
                            2
                        ]
                    ],
                    "types": [
                        [
                            "Q"
                        ]
                    ]
                }
            },
            "coefficient_blocks": [
                {
                    "module": "pygsti.modelmembers.operations.lindbladcoefficients",
                    "class": "LindbladCoefficientBlock",
                    "version": 0,
                    "block_type": "ham",
                    "parameterization_mode": "elements",
                    "basis_element_labels": [
                        "X",
                        "Y",
                        "Z"
                    ],
                    "basis": {
                        "module": "pygsti.baseobjs.basis",
                        "class": "BuiltinBasis",
                        "version": 0,
                        "name": "PP",
                        "sparse": true,
                        "state_space": {
                            "module": "pygsti.baseobjs.statespace",
                            "class": "QubitSpace",
                            "version": 0,
                            "qudit_labels": [
                                0
                            ],
                            "qudit_udims": [
                                2
                            ],
                            "qubit_labels": [
                                0
                            ]
                        }
                    },
                    "block_data": [
                        0.1275931440752808,
                        0.4256657057287149,
                        -0.06805120516811493
                    ]
                },
                {
                    "module": "pygsti.modelmembers.operations.lindbladcoefficients",
                    "class": "LindbladCoefficientBlock",
                    "version": 0,
                    "block_type": "other",
                    "parameterization_mode": "cholesky",
                    "basis_element_labels": [
                        "X",
                        "Y",
                        "Z"
                    ],
                    "basis": {
                        "module": "pygsti.baseobjs.basis",
                        "class": "BuiltinBasis",
                        "version": 0,
                        "name": "PP",
                        "sparse": true,
                        "state_space": {
                            "module": "pygsti.baseobjs.statespace",
                            "class": "QubitSpace",
                            "version": 0,
                            "qudit_labels": [
                                0
                            ],
                            "qudit_udims": [
                                2
                            ],
                            "qubit_labels": [
                                0
                            ]
                        }
                    },
                    "block_data": [
                        [
                            "(0.08386777340120814+0j)",
                            "(-0.04520476799982831-0.02275643564632635j)",
                            "(0.0415053747200973+0.01911798120580017j)"
                        ],
                        [
                            "(-0.04520476799982831+0.02275643564632635j)",
                            "(0.03652335409684816+0j)",
                            "(-0.03647523766032401+0.012147761961699224j)"
                        ],
                        [
                            "(0.0415053747200973-0.01911798120580017j)",
                            "(-0.03647523766032401-0.012147761961699224j)",
                            "(0.05911515984096538+0j)"
                        ]
                    ]
                }
            ]
        },
        "14": {
            "module": "pygsti.modelmembers.operations.experrorgenop",
            "class": "ExpErrorgenOp",
            "submembers": [
                13
            ],
            "state_space": {
                "module": "pygsti.baseobjs.statespace",
                "class": "ExplicitStateSpace",
                "version": 0,
                "labels": [
                    [
                        0
                    ]
                ],
                "unitary_space_dimensions": [
                    [
                        2
                    ]
                ],
                "types": [
                    [
                        "Q"
                    ]
                ]
            },
            "evotype": "densitymx",
            "model_parameter_indices": [
                36,
                37,
                38,
                39,
                40,
                41,
                42,
                43,
                44,
                45,
                46,
                47
            ],
            "relative_submember_parameter_indices": [
                [
                    0,
                    1,
                    2,
                    3,
                    4,
                    5,
                    6,
                    7,
                    8,
                    9,
                    10,
                    11
                ]
            ],
            "parameter_labels": null,
            "parameter_bounds": null
        },
        "15": {
            "module": "pygsti.modelmembers.operations.composedop",
            "class": "ComposedOp",
            "submembers": [
                12,
                14
            ],
            "state_space": {
                "module": "pygsti.baseobjs.statespace",
                "class": "ExplicitStateSpace",
                "version": 0,
                "labels": [
                    [
                        0
                    ]
                ],
                "unitary_space_dimensions": [
                    [
                        2
                    ]
                ],
                "types": [
                    [
                        "Q"
                    ]
                ]
            },
            "evotype": "densitymx",
            "model_parameter_indices": [
                36,
                37,
                38,
                39,
                40,
                41,
                42,
                43,
                44,
                45,
                46,
                47
            ],
            "relative_submember_parameter_indices": [
                [],
                [
                    0,
                    1,
                    2,
                    3,
                    4,
                    5,
                    6,
                    7,
                    8,
                    9,
                    10,
                    11
                ]
            ],
            "parameter_labels": null,
            "parameter_bounds": null,
            "memberdict_types": [
                "operations"
            ],
            "memberdict_labels": [
                "Gxpi2:0"
            ]
        },
        "16": {
            "module": "pygsti.modelmembers.operations.staticunitaryop",
            "class": "StaticUnitaryOp",
            "submembers": [],
            "state_space": {
                "module": "pygsti.baseobjs.statespace",
                "class": "ExplicitStateSpace",
                "version": 0,
                "labels": [
                    [
                        0
                    ]
                ],
                "unitary_space_dimensions": [
                    [
                        2
                    ]
                ],
                "types": [
                    [
                        "Q"
                    ]
                ]
            },
            "evotype": "densitymx",
            "model_parameter_indices": [],
            "relative_submember_parameter_indices": [],
            "parameter_labels": null,
            "parameter_bounds": null,
            "dense_matrix": [
                [
                    "(0.7071067811865475+0j)",
                    "(-0.7071067811865475+0j)"
                ],
                [
                    "(0.7071067811865477+0j)",
                    "(0.7071067811865477+0j)"
                ]
            ],
            "basis": {
                "module": "pygsti.baseobjs.basis",
                "class": "BuiltinBasis",
                "version": 0,
                "name": "pp",
                "sparse": false,
                "state_space": {
                    "module": "pygsti.baseobjs.statespace",
                    "class": "ExplicitStateSpace",
                    "version": 0,
                    "labels": [
                        [
                            0
                        ]
                    ],
                    "unitary_space_dimensions": [
                        [
                            2
                        ]
                    ],
                    "types": [
                        [
                            "Q"
                        ]
                    ]
                }
            }
        },
        "17": {
            "module": "pygsti.modelmembers.operations.lindbladerrorgen",
            "class": "LindbladErrorgen",
            "submembers": [],
            "state_space": {
                "module": "pygsti.baseobjs.statespace",
                "class": "ExplicitStateSpace",
                "version": 0,
                "labels": [
                    [
                        0
                    ]
                ],
                "unitary_space_dimensions": [
                    [
                        2
                    ]
                ],
                "types": [
                    [
                        "Q"
                    ]
                ]
            },
            "evotype": "densitymx",
            "model_parameter_indices": [
                48,
                49,
                50,
                51,
                52,
                53,
                54,
                55,
                56,
                57,
                58,
                59
            ],
            "relative_submember_parameter_indices": [],
            "parameter_labels": [
                "X Hamiltonian error coefficient",
                "Y Hamiltonian error coefficient",
                "Z Hamiltonian error coefficient",
                "X diagonal element of non-H coeff Cholesky decomp",
                "Im[(X,Y) element of non-H coeff Cholesky decomp]",
                "Im[(X,Z) element of non-H coeff Cholesky decomp]",
                "Re[(Y,X) element of non-H coeff Cholesky decomp]",
                "Y diagonal element of non-H coeff Cholesky decomp",
                "Im[(Y,Z) element of non-H coeff Cholesky decomp]",
                "Re[(Z,X) element of non-H coeff Cholesky decomp]",
                "Re[(Z,Y) element of non-H coeff Cholesky decomp]",
                "Z diagonal element of non-H coeff Cholesky decomp"
            ],
            "parameter_bounds": null,
            "rep_type": "sparse superop",
            "matrix_basis": {
                "module": "pygsti.baseobjs.basis",
                "class": "BuiltinBasis",
                "version": 0,
                "name": "pp",
                "sparse": true,
                "state_space": {
                    "module": "pygsti.baseobjs.statespace",
                    "class": "ExplicitStateSpace",
                    "version": 0,
                    "labels": [
                        [
                            0
                        ]
                    ],
                    "unitary_space_dimensions": [
                        [
                            2
                        ]
                    ],
                    "types": [
                        [
                            "Q"
                        ]
                    ]
                }
            },
            "coefficient_blocks": [
                {
                    "module": "pygsti.modelmembers.operations.lindbladcoefficients",
                    "class": "LindbladCoefficientBlock",
                    "version": 0,
                    "block_type": "ham",
                    "parameterization_mode": "elements",
                    "basis_element_labels": [
                        "X",
                        "Y",
                        "Z"
                    ],
                    "basis": {
                        "module": "pygsti.baseobjs.basis",
                        "class": "BuiltinBasis",
                        "version": 0,
                        "name": "PP",
                        "sparse": true,
                        "state_space": {
                            "module": "pygsti.baseobjs.statespace",
                            "class": "QubitSpace",
                            "version": 0,
                            "qudit_labels": [
                                0
                            ],
                            "qudit_udims": [
                                2
                            ],
                            "qubit_labels": [
                                0
                            ]
                        }
                    },
                    "block_data": [
                        -0.26598911498084676,
                        0.14827296227890502,
                        0.0945078257899318
                    ]
                },
                {
                    "module": "pygsti.modelmembers.operations.lindbladcoefficients",
                    "class": "LindbladCoefficientBlock",
                    "version": 0,
                    "block_type": "other",
                    "parameterization_mode": "cholesky",
                    "basis_element_labels": [
                        "X",
                        "Y",
                        "Z"
                    ],
                    "basis": {
                        "module": "pygsti.baseobjs.basis",
                        "class": "BuiltinBasis",
                        "version": 0,
                        "name": "PP",
                        "sparse": true,
                        "state_space": {
                            "module": "pygsti.baseobjs.statespace",
                            "class": "QubitSpace",
                            "version": 0,
                            "qudit_labels": [
                                0
                            ],
                            "qudit_udims": [
                                2
                            ],
                            "qubit_labels": [
                                0
                            ]
                        }
                    },
                    "block_data": [
                        [
                            "(0.08189940648555533+0j)",
                            "(-0.043223164612331944-0.03684450110999823j)",
                            "(-0.032480888388130166+0.0019070258277046617j)"
                        ],
                        [
                            "(-0.043223164612331944+0.03684450110999823j)",
                            "(0.04314369667384444+0j)",
                            "(0.019187055456489223-0.01352004631025222j)"
                        ],
                        [
                            "(-0.032480888388130166-0.0019070258277046617j)",
                            "(0.019187055456489223+0.01352004631025222j)",
                            "(0.01634165660945244+0j)"
                        ]
                    ]
                }
            ]
        },
        "18": {
            "module": "pygsti.modelmembers.operations.experrorgenop",
            "class": "ExpErrorgenOp",
            "submembers": [
                17
            ],
            "state_space": {
                "module": "pygsti.baseobjs.statespace",
                "class": "ExplicitStateSpace",
                "version": 0,
                "labels": [
                    [
                        0
                    ]
                ],
                "unitary_space_dimensions": [
                    [
                        2
                    ]
                ],
                "types": [
                    [
                        "Q"
                    ]
                ]
            },
            "evotype": "densitymx",
            "model_parameter_indices": [
                48,
                49,
                50,
                51,
                52,
                53,
                54,
                55,
                56,
                57,
                58,
                59
            ],
            "relative_submember_parameter_indices": [
                [
                    0,
                    1,
                    2,
                    3,
                    4,
                    5,
                    6,
                    7,
                    8,
                    9,
                    10,
                    11
                ]
            ],
            "parameter_labels": null,
            "parameter_bounds": null
        },
        "19": {
            "module": "pygsti.modelmembers.operations.composedop",
            "class": "ComposedOp",
            "submembers": [
                16,
                18
            ],
            "state_space": {
                "module": "pygsti.baseobjs.statespace",
                "class": "ExplicitStateSpace",
                "version": 0,
                "labels": [
                    [
                        0
                    ]
                ],
                "unitary_space_dimensions": [
                    [
                        2
                    ]
                ],
                "types": [
                    [
                        "Q"
                    ]
                ]
            },
            "evotype": "densitymx",
            "model_parameter_indices": [
                48,
                49,
                50,
                51,
                52,
                53,
                54,
                55,
                56,
                57,
                58,
                59
            ],
            "relative_submember_parameter_indices": [
                [],
                [
                    0,
                    1,
                    2,
                    3,
                    4,
                    5,
                    6,
                    7,
                    8,
                    9,
                    10,
                    11
                ]
            ],
            "parameter_labels": null,
            "parameter_bounds": null,
            "memberdict_types": [
                "operations"
            ],
            "memberdict_labels": [
                "Gypi2:0"
            ]
        },
        "20": {
            "module": "pygsti.modelmembers.operations.staticunitaryop",
            "class": "StaticUnitaryOp",
            "submembers": [],
            "state_space": {
                "module": "pygsti.baseobjs.statespace",
                "class": "ExplicitStateSpace",
                "version": 0,
                "labels": [
                    [
                        0
                    ]
                ],
                "unitary_space_dimensions": [
                    [
                        2
                    ]
                ],
                "types": [
                    [
                        "Q"
                    ]
                ]
            },
            "evotype": "densitymx",
            "model_parameter_indices": [],
            "relative_submember_parameter_indices": [],
            "parameter_labels": null,
            "parameter_bounds": null,
            "dense_matrix": [
                [
                    "0j",
                    "(1+0j)"
                ],
                [
                    "(1+0j)",
                    "0j"
                ]
            ],
            "basis": {
                "module": "pygsti.baseobjs.basis",
                "class": "BuiltinBasis",
                "version": 0,
                "name": "pp",
                "sparse": false,
                "state_space": {
                    "module": "pygsti.baseobjs.statespace",
                    "class": "ExplicitStateSpace",
                    "version": 0,
                    "labels": [
                        [
                            0
                        ]
                    ],
                    "unitary_space_dimensions": [
                        [
                            2
                        ]
                    ],
                    "types": [
                        [
                            "Q"
                        ]
                    ]
                }
            }
        },
        "21": {
            "module": "pygsti.modelmembers.operations.lindbladerrorgen",
            "class": "LindbladErrorgen",
            "submembers": [],
            "state_space": {
                "module": "pygsti.baseobjs.statespace",
                "class": "ExplicitStateSpace",
                "version": 0,
                "labels": [
                    [
                        0
                    ]
                ],
                "unitary_space_dimensions": [
                    [
                        2
                    ]
                ],
                "types": [
                    [
                        "Q"
                    ]
                ]
            },
            "evotype": "densitymx",
            "model_parameter_indices": [
                60,
                61,
                62,
                63,
                64,
                65,
                66,
                67,
                68,
                69,
                70,
                71
            ],
            "relative_submember_parameter_indices": [],
            "parameter_labels": [
                "X Hamiltonian error coefficient",
                "Y Hamiltonian error coefficient",
                "Z Hamiltonian error coefficient",
                "X diagonal element of non-H coeff Cholesky decomp",
                "Im[(X,Y) element of non-H coeff Cholesky decomp]",
                "Im[(X,Z) element of non-H coeff Cholesky decomp]",
                "Re[(Y,X) element of non-H coeff Cholesky decomp]",
                "Y diagonal element of non-H coeff Cholesky decomp",
                "Im[(Y,Z) element of non-H coeff Cholesky decomp]",
                "Re[(Z,X) element of non-H coeff Cholesky decomp]",
                "Re[(Z,Y) element of non-H coeff Cholesky decomp]",
                "Z diagonal element of non-H coeff Cholesky decomp"
            ],
            "parameter_bounds": null,
            "rep_type": "sparse superop",
            "matrix_basis": {
                "module": "pygsti.baseobjs.basis",
                "class": "BuiltinBasis",
                "version": 0,
                "name": "pp",
                "sparse": true,
                "state_space": {
                    "module": "pygsti.baseobjs.statespace",
                    "class": "ExplicitStateSpace",
                    "version": 0,
                    "labels": [
                        [
                            0
                        ]
                    ],
                    "unitary_space_dimensions": [
                        [
                            2
                        ]
                    ],
                    "types": [
                        [
                            "Q"
                        ]
                    ]
                }
            },
            "coefficient_blocks": [
                {
                    "module": "pygsti.modelmembers.operations.lindbladcoefficients",
                    "class": "LindbladCoefficientBlock",
                    "version": 0,
                    "block_type": "ham",
                    "parameterization_mode": "elements",
                    "basis_element_labels": [
                        "X",
                        "Y",
                        "Z"
                    ],
                    "basis": {
                        "module": "pygsti.baseobjs.basis",
                        "class": "BuiltinBasis",
                        "version": 0,
                        "name": "PP",
                        "sparse": true,
                        "state_space": {
                            "module": "pygsti.baseobjs.statespace",
                            "class": "QubitSpace",
                            "version": 0,
                            "qudit_labels": [
                                0
                            ],
                            "qudit_udims": [
                                2
                            ],
                            "qubit_labels": [
                                0
                            ]
                        }
                    },
                    "block_data": [
                        -0.004861272308563009,
                        0.32736196073755136,
                        0.30612238202590647
                    ]
                },
                {
                    "module": "pygsti.modelmembers.operations.lindbladcoefficients",
                    "class": "LindbladCoefficientBlock",
                    "version": 0,
                    "block_type": "other",
                    "parameterization_mode": "cholesky",
                    "basis_element_labels": [
                        "X",
                        "Y",
                        "Z"
                    ],
                    "basis": {
                        "module": "pygsti.baseobjs.basis",
                        "class": "BuiltinBasis",
                        "version": 0,
                        "name": "PP",
                        "sparse": true,
                        "state_space": {
                            "module": "pygsti.baseobjs.statespace",
                            "class": "QubitSpace",
                            "version": 0,
                            "qudit_labels": [
                                0
                            ],
                            "qudit_udims": [
                                2
                            ],
                            "qubit_labels": [
                                0
                            ]
                        }
                    },
                    "block_data": [
                        [
                            "(0.04735154165497857+0j)",
                            "(0.023007196158143534-0.03529288363557005j)",
                            "(-0.004371791940526016-0.00410525997540917j)"
                        ],
                        [
                            "(0.023007196158143534+0.03529288363557005j)",
                            "(0.03748386321412708+0j)",
                            "(0.0009356355953619947-0.005253127080483894j)"
                        ],
                        [
                            "(-0.004371791940526016+0.00410525997540917j)",
                            "(0.0009356355953619947+0.005253127080483894j)",
                            "(0.0007595470597202743+0j)"
                        ]
                    ]
                }
            ]
        },
        "22": {
            "module": "pygsti.modelmembers.operations.experrorgenop",
            "class": "ExpErrorgenOp",
            "submembers": [
                21
            ],
            "state_space": {
                "module": "pygsti.baseobjs.statespace",
                "class": "ExplicitStateSpace",
                "version": 0,
                "labels": [
                    [
                        0
                    ]
                ],
                "unitary_space_dimensions": [
                    [
                        2
                    ]
                ],
                "types": [
                    [
                        "Q"
                    ]
                ]
            },
            "evotype": "densitymx",
            "model_parameter_indices": [
                60,
                61,
                62,
                63,
                64,
                65,
                66,
                67,
                68,
                69,
                70,
                71
            ],
            "relative_submember_parameter_indices": [
                [
                    0,
                    1,
                    2,
                    3,
                    4,
                    5,
                    6,
                    7,
                    8,
                    9,
                    10,
                    11
                ]
            ],
            "parameter_labels": null,
            "parameter_bounds": null
        },
        "23": {
            "module": "pygsti.modelmembers.operations.composedop",
            "class": "ComposedOp",
            "submembers": [
                20,
                22
            ],
            "state_space": {
                "module": "pygsti.baseobjs.statespace",
                "class": "ExplicitStateSpace",
                "version": 0,
                "labels": [
                    [
                        0
                    ]
                ],
                "unitary_space_dimensions": [
                    [
                        2
                    ]
                ],
                "types": [
                    [
                        "Q"
                    ]
                ]
            },
            "evotype": "densitymx",
            "model_parameter_indices": [
                60,
                61,
                62,
                63,
                64,
                65,
                66,
                67,
                68,
                69,
                70,
                71
            ],
            "relative_submember_parameter_indices": [
                [],
                [
                    0,
                    1,
                    2,
                    3,
                    4,
                    5,
                    6,
                    7,
                    8,
                    9,
                    10,
                    11
                ]
            ],
            "parameter_labels": null,
            "parameter_bounds": null,
            "memberdict_types": [
                "operations"
            ],
            "memberdict_labels": [
                "Gxpi:0"
            ]
        },
        "24": {
            "module": "pygsti.modelmembers.operations.staticunitaryop",
            "class": "StaticUnitaryOp",
            "submembers": [],
            "state_space": {
                "module": "pygsti.baseobjs.statespace",
                "class": "ExplicitStateSpace",
                "version": 0,
                "labels": [
                    [
                        0
                    ]
                ],
                "unitary_space_dimensions": [
                    [
                        2
                    ]
                ],
                "types": [
                    [
                        "Q"
                    ]
                ]
            },
            "evotype": "densitymx",
            "model_parameter_indices": [],
            "relative_submember_parameter_indices": [],
            "parameter_labels": null,
            "parameter_bounds": null,
            "dense_matrix": [
                [
                    "0j",
                    "(-1+0j)"
                ],
                [
                    "(1+0j)",
                    "0j"
                ]
            ],
            "basis": {
                "module": "pygsti.baseobjs.basis",
                "class": "BuiltinBasis",
                "version": 0,
                "name": "pp",
                "sparse": false,
                "state_space": {
                    "module": "pygsti.baseobjs.statespace",
                    "class": "ExplicitStateSpace",
                    "version": 0,
                    "labels": [
                        [
                            0
                        ]
                    ],
                    "unitary_space_dimensions": [
                        [
                            2
                        ]
                    ],
                    "types": [
                        [
                            "Q"
                        ]
                    ]
                }
            }
        },
        "25": {
            "module": "pygsti.modelmembers.operations.lindbladerrorgen",
            "class": "LindbladErrorgen",
            "submembers": [],
            "state_space": {
                "module": "pygsti.baseobjs.statespace",
                "class": "ExplicitStateSpace",
                "version": 0,
                "labels": [
                    [
                        0
                    ]
                ],
                "unitary_space_dimensions": [
                    [
                        2
                    ]
                ],
                "types": [
                    [
                        "Q"
                    ]
                ]
            },
            "evotype": "densitymx",
            "model_parameter_indices": [
                72,
                73,
                74,
                75,
                76,
                77,
                78,
                79,
                80,
                81,
                82,
                83
            ],
            "relative_submember_parameter_indices": [],
            "parameter_labels": [
                "X Hamiltonian error coefficient",
                "Y Hamiltonian error coefficient",
                "Z Hamiltonian error coefficient",
                "X diagonal element of non-H coeff Cholesky decomp",
                "Im[(X,Y) element of non-H coeff Cholesky decomp]",
                "Im[(X,Z) element of non-H coeff Cholesky decomp]",
                "Re[(Y,X) element of non-H coeff Cholesky decomp]",
                "Y diagonal element of non-H coeff Cholesky decomp",
                "Im[(Y,Z) element of non-H coeff Cholesky decomp]",
                "Re[(Z,X) element of non-H coeff Cholesky decomp]",
                "Re[(Z,Y) element of non-H coeff Cholesky decomp]",
                "Z diagonal element of non-H coeff Cholesky decomp"
            ],
            "parameter_bounds": null,
            "rep_type": "sparse superop",
            "matrix_basis": {
                "module": "pygsti.baseobjs.basis",
                "class": "BuiltinBasis",
                "version": 0,
                "name": "pp",
                "sparse": true,
                "state_space": {
                    "module": "pygsti.baseobjs.statespace",
                    "class": "ExplicitStateSpace",
                    "version": 0,
                    "labels": [
                        [
                            0
                        ]
                    ],
                    "unitary_space_dimensions": [
                        [
                            2
                        ]
                    ],
                    "types": [
                        [
                            "Q"
                        ]
                    ]
                }
            },
            "coefficient_blocks": [
                {
                    "module": "pygsti.modelmembers.operations.lindbladcoefficients",
                    "class": "LindbladCoefficientBlock",
                    "version": 0,
                    "block_type": "ham",
                    "parameterization_mode": "elements",
                    "basis_element_labels": [
                        "X",
                        "Y",
                        "Z"
                    ],
                    "basis": {
                        "module": "pygsti.baseobjs.basis",
                        "class": "BuiltinBasis",
                        "version": 0,
                        "name": "PP",
                        "sparse": true,
                        "state_space": {
                            "module": "pygsti.baseobjs.statespace",
                            "class": "QubitSpace",
                            "version": 0,
                            "qudit_labels": [
                                0
                            ],
                            "qudit_udims": [
                                2
                            ],
                            "qubit_labels": [
                                0
                            ]
                        }
                    },
                    "block_data": [
                        -0.3411789985330198,
                        -0.03593559076863832,
                        0.3876466680430929
                    ]
                },
                {
                    "module": "pygsti.modelmembers.operations.lindbladcoefficients",
                    "class": "LindbladCoefficientBlock",
                    "version": 0,
                    "block_type": "other",
                    "parameterization_mode": "cholesky",
                    "basis_element_labels": [
                        "X",
                        "Y",
                        "Z"
                    ],
                    "basis": {
                        "module": "pygsti.baseobjs.basis",
                        "class": "BuiltinBasis",
                        "version": 0,
                        "name": "PP",
                        "sparse": true,
                        "state_space": {
                            "module": "pygsti.baseobjs.statespace",
                            "class": "QubitSpace",
                            "version": 0,
                            "qudit_labels": [
                                0
                            ],
                            "qudit_udims": [
                                2
                            ],
                            "qubit_labels": [
                                0
                            ]
                        }
                    },
                    "block_data": [
                        [
                            "(0.03840814490535116+0j)",
                            "(-0.0024042961765966407-0.007266471995385258j)",
                            "(-0.015429748052722165+0.012573246358585392j)"
                        ],
                        [
                            "(-0.0024042961765966407+0.007266471995385258j)",
                            "(0.05629286592070021+0j)",
                            "(-0.01046909823399229-0.03270437037387726j)"
                        ],
                        [
                            "(-0.015429748052722165-0.012573246358585392j)",
                            "(-0.01046909823399229+0.03270437037387726j)",
                            "(0.02716590636100972+0j)"
                        ]
                    ]
                }
            ]
        },
        "26": {
            "module": "pygsti.modelmembers.operations.experrorgenop",
            "class": "ExpErrorgenOp",
            "submembers": [
                25
            ],
            "state_space": {
                "module": "pygsti.baseobjs.statespace",
                "class": "ExplicitStateSpace",
                "version": 0,
                "labels": [
                    [
                        0
                    ]
                ],
                "unitary_space_dimensions": [
                    [
                        2
                    ]
                ],
                "types": [
                    [
                        "Q"
                    ]
                ]
            },
            "evotype": "densitymx",
            "model_parameter_indices": [
                72,
                73,
                74,
                75,
                76,
                77,
                78,
                79,
                80,
                81,
                82,
                83
            ],
            "relative_submember_parameter_indices": [
                [
                    0,
                    1,
                    2,
                    3,
                    4,
                    5,
                    6,
                    7,
                    8,
                    9,
                    10,
                    11
                ]
            ],
            "parameter_labels": null,
            "parameter_bounds": null
        },
        "27": {
            "module": "pygsti.modelmembers.operations.composedop",
            "class": "ComposedOp",
            "submembers": [
                24,
                26
            ],
            "state_space": {
                "module": "pygsti.baseobjs.statespace",
                "class": "ExplicitStateSpace",
                "version": 0,
                "labels": [
                    [
                        0
                    ]
                ],
                "unitary_space_dimensions": [
                    [
                        2
                    ]
                ],
                "types": [
                    [
                        "Q"
                    ]
                ]
            },
            "evotype": "densitymx",
            "model_parameter_indices": [
                72,
                73,
                74,
                75,
                76,
                77,
                78,
                79,
                80,
                81,
                82,
                83
            ],
            "relative_submember_parameter_indices": [
                [],
                [
                    0,
                    1,
                    2,
                    3,
                    4,
                    5,
                    6,
                    7,
                    8,
                    9,
                    10,
                    11
                ]
            ],
            "parameter_labels": null,
            "parameter_bounds": null,
            "memberdict_types": [
                "operations"
            ],
            "memberdict_labels": [
                "Gypi:0"
            ]
        }
    }
}